ironoak/__init__.py
ironoak/__main__.py
ironoak/cli.py
ironoak/aiming/__init__.py
ironoak/aiming/aiming.py
ironoak-0.0.0.dist-info/AUTHORS.rst
ironoak-0.0.0.dist-info/LICENSE
ironoak-0.0.0.dist-info/METADATA
ironoak-0.0.0.dist-info/WHEEL
ironoak-0.0.0.dist-info/entry_points.txt
ironoak-0.0.0.dist-info/top_level.txt
ironoak-0.0.0.dist-info/RECORD
