Metadata-Version: 2.1
Name: ironoak
Version: 0.0.0
Summary: A package for a convenient interface to oak cameras.
Home-page: https://github.com/prasannavk/python-ironoak
Author: Prasanna Krishnasamy
Author-email: krishnasamy.prasanna@gmail.com
License: Apache-2.0
Project-URL: Documentation, https://python-ironoak.readthedocs.io/
Project-URL: Changelog, https://python-ironoak.readthedocs.io/en/latest/changelog.html
Project-URL: Issue Tracker, https://github.com/prasannavk/python-ironoak/issues
Classifier: Development Status :: 5 - Production/Stable
Classifier: Intended Audience :: Developers
Classifier: License :: OSI Approved :: Apache Software License
Classifier: Operating System :: Unix
Classifier: Operating System :: POSIX
Classifier: Operating System :: Microsoft :: Windows
Classifier: Programming Language :: Python
Classifier: Programming Language :: Python :: 3
Classifier: Programming Language :: Python :: 3 :: Only
Classifier: Programming Language :: Python :: 3.6
Classifier: Programming Language :: Python :: 3.7
Classifier: Programming Language :: Python :: 3.8
Classifier: Programming Language :: Python :: 3.9
Classifier: Programming Language :: Python :: 3.10
Classifier: Programming Language :: Python :: Implementation :: CPython
Classifier: Programming Language :: Python :: Implementation :: PyPy
Classifier: Topic :: Utilities
Requires-Python: >=3.6
License-File: LICENSE
License-File: AUTHORS.rst
